neuondb/__init__.py
neuondb/neuondb.py
neuondb-0.1.5.dist-info/METADATA
neuondb-0.1.5.dist-info/WHEEL
neuondb-0.1.5.dist-info/top_level.txt
neuondb-0.1.5.dist-info/RECORD
